LICENSE
README.md
setup.py
Orange3_Tools.egg-info/PKG-INFO
Orange3_Tools.egg-info/SOURCES.txt
Orange3_Tools.egg-info/dependency_links.txt
Orange3_Tools.egg-info/entry_points.txt
Orange3_Tools.egg-info/not-zip-safe
Orange3_Tools.egg-info/requires.txt
Orange3_Tools.egg-info/top_level.txt
orangecontrib/__init__.py
orangecontrib/functions.py
orangecontrib/tools/__init__.py
orangecontrib/tools/widgets/MySqlOrange.py
orangecontrib/tools/widgets/Pairsplot.py
orangecontrib/tools/widgets/Scatterplot.py
orangecontrib/tools/widgets/__init__.py
orangecontrib/tools/widgets/my_widget.py
orangecontrib/tools/widgets/mymessages.py
orangecontrib/tools/widgets/mywidgets.py
orangecontrib/tools/widgets/owcorrelogram.py
orangecontrib/tools/widgets/owsarima.py
orangecontrib/tools/widgets/owstationarity.py
orangecontrib/tools/widgets/utils.py
orangecontrib/tools/widgets/icons/ARIMA.svg
orangecontrib/tools/widgets/icons/Barchart.svg
orangecontrib/tools/widgets/icons/Correlogram.svg
orangecontrib/tools/widgets/icons/Dlg_arrow.png
orangecontrib/tools/widgets/icons/Dlg_clear.png
orangecontrib/tools/widgets/icons/Dlg_down3.png
orangecontrib/tools/widgets/icons/Dlg_enter.png
orangecontrib/tools/widgets/icons/Dlg_pan_hand.png
orangecontrib/tools/widgets/icons/Dlg_redo.png
orangecontrib/tools/widgets/icons/Dlg_send.png
orangecontrib/tools/widgets/icons/Dlg_sort.png
orangecontrib/tools/widgets/icons/Dlg_undo.png
orangecontrib/tools/widgets/icons/Dlg_up3.png
orangecontrib/tools/widgets/icons/Dlg_zoom.png
orangecontrib/tools/widgets/icons/Dlg_zoom_reset.png
orangecontrib/tools/widgets/icons/Dlg_zoom_selection.png
orangecontrib/tools/widgets/icons/Pairs.svg
orangecontrib/tools/widgets/icons/Simple_scatterplot.svg
orangecontrib/tools/widgets/icons/Unknown.png
orangecontrib/tools/widgets/icons/category.svg
orangecontrib/tools/widgets/icons/chart.svg
orangecontrib/tools/widgets/icons/downgreenarrow.png
orangecontrib/tools/widgets/icons/error.png
orangecontrib/tools/widgets/icons/hamburger.svg
orangecontrib/tools/widgets/icons/help.svg
orangecontrib/tools/widgets/icons/information.png
orangecontrib/tools/widgets/icons/input-empty.svg
orangecontrib/tools/widgets/icons/input-partial.svg
orangecontrib/tools/widgets/icons/input.svg
