Metadata-Version: 2.1
Name: Orange3-Tools
Version: 0.0.10
Summary: Tools para Asignatura Big Data Master EERR
Home-page: 
Download-URL: 
Author: Julio J. Melero
Author-email: melero@unizar.es
License: GPL-3.0
Keywords: orange3 add-on
License-File: LICENSE
Requires-Dist: anyqt
Requires-Dist: pandas
Requires-Dist: BeautifulSoup4
Requires-Dist: numpy
Requires-Dist: seaborn
Requires-Dist: Orange3>=3.31.1
Requires-Dist: orange-widget-base
Requires-Dist: scikit-learn
Requires-Dist: pyqtgraph
Requires-Dist: mysql-connector-python
Provides-Extra: doc
Requires-Dist: sphinx; extra == "doc"
Requires-Dist: recommonmark; extra == "doc"
Requires-Dist: sphinx_rtd_theme; extra == "doc"
Provides-Extra: test
Requires-Dist: coverage; extra == "test"
